{
  "id": "a4b6fac8-d336-4a58-9235-62c02fb23614",
  "type": "dre",
  "payload": {
    "codiEmp": 90124,
    "dataInicial": "2025-06-01",
    "dataFinal": "2025-06-30",
    "ingles": true
  },
  "status": "complete",
  "progress": 100,
  "result": {
    "raw": "Gerando DRE em inglês - Empresa: 90124, Período: 2025-06-01 a 2025-06-30\r\nTimestamp da execução: 20250827_151345\r\nAviso: Não foram encontradas traduções em inglês no banco. Usando textos em português com interface em inglês.\r\nConexão com o banco de dados bem-sucedida.\r\nExecutando consulta: estrutura_dre_completa_tipo2...\r\nConsulta estrutura_dre_completa_tipo2 retornou 0 linhas.\r\nExecutando consulta: cabecalho_empresa...\r\nConsulta cabecalho_empresa retornou 0 linhas.\r\nExecutando consulta: cabecalho_contador...\r\nConsulta cabecalho_contador retornou 1 linhas.\r\nExecutando consulta: cabecalho_administrador...\r\nConsulta cabecalho_administrador retornou 1 linhas.\r\nExecutando consulta: saldos_contas...\r\nConsulta saldos_contas retornou 0 linhas.\r\nConexão fechada.\r\nDados salvos em 'dados_dre_EMP90124_20250601_a_20250630_EN_20250827_151345.json'\r\n{\"error\": \"list index out of range\"}\r\n",
    "code": 1
  },
  "error": null,
  "createdAt": 1756318406188,
  "startedAt": 1756318424513
}